sctrader/__init__.py
sctrader/api.py
sctrader/clienttrader.py
sctrader/exceptions.py
sctrader/follower.py
sctrader/gf_clienttrader.py
sctrader/gj_clienttrader.py
sctrader/grid_strategies.py
sctrader/ht_clienttrader.py
sctrader/htzq_clienttrader.py
sctrader/joinquant_follower.py
sctrader/log.py
sctrader/pop_dialog_handler.py
sctrader/refresh_strategies.py
sctrader/remoteclient.py
sctrader/ricequant_follower.py
sctrader/server.py
sctrader/universal_clienttrader.py
sctrader/webtrader.py
sctrader/wk_clienttrader.py
sctrader/xq_follower.py
sctrader/xqtrader.py
sctrader/yh_clienttrader.py
sctrader/config/__init__.py
sctrader/config/client.py
sctrader/config/global.json
sctrader/config/xq.json
sctrader/utils/__init__.py
sctrader/utils/captcha.py
sctrader/utils/misc.py
sctrader/utils/perf.py
sctrader/utils/stock.py
sctrader/utils/win_gui.py
sctrader-1.0.1.dist-info/LICENSE
sctrader-1.0.1.dist-info/METADATA
sctrader-1.0.1.dist-info/WHEEL
sctrader-1.0.1.dist-info/top_level.txt
sctrader-1.0.1.dist-info/RECORD
